ezcad/__init__.cp37-win_amd64.exp
ezcad/__init__.cp37-win_amd64.lib
ezcad/__init__.cp37-win_amd64.pyd
ezcad/__main__.py
ezcad/license.cp37-win_amd64.exp
ezcad/license.cp37-win_amd64.lib
ezcad/license.cp37-win_amd64.pyd
ezcad/app/__init__.cp37-win_amd64.exp
ezcad/app/__init__.cp37-win_amd64.lib
ezcad/app/__init__.cp37-win_amd64.pyd
ezcad/app/launch_options.cp37-win_amd64.exp
ezcad/app/launch_options.cp37-win_amd64.lib
ezcad/app/launch_options.cp37-win_amd64.pyd
ezcad/app/main.cp37-win_amd64.exp
ezcad/app/main.cp37-win_amd64.lib
ezcad/app/main.cp37-win_amd64.pyd
ezcad/app/mainwindow.cp37-win_amd64.exp
ezcad/app/mainwindow.cp37-win_amd64.lib
ezcad/app/mainwindow.cp37-win_amd64.pyd
ezcad/config/__init__.cp37-win_amd64.exp
ezcad/config/__init__.cp37-win_amd64.lib
ezcad/config/__init__.cp37-win_amd64.pyd
ezcad/config/base.cp37-win_amd64.exp
ezcad/config/base.cp37-win_amd64.lib
ezcad/config/base.cp37-win_amd64.pyd
ezcad/config/fonts.cp37-win_amd64.exp
ezcad/config/fonts.cp37-win_amd64.lib
ezcad/config/fonts.cp37-win_amd64.pyd
ezcad/config/gui.cp37-win_amd64.exp
ezcad/config/gui.cp37-win_amd64.lib
ezcad/config/gui.cp37-win_amd64.pyd
ezcad/config/main.cp37-win_amd64.exp
ezcad/config/main.cp37-win_amd64.lib
ezcad/config/main.cp37-win_amd64.pyd
ezcad/config/user.cp37-win_amd64.exp
ezcad/config/user.cp37-win_amd64.lib
ezcad/config/user.cp37-win_amd64.pyd
ezcad/config/utils.cp37-win_amd64.exp
ezcad/config/utils.cp37-win_amd64.lib
ezcad/config/utils.cp37-win_amd64.pyd
ezcad/dialogs/__init__.cp37-win_amd64.exp
ezcad/dialogs/__init__.cp37-win_amd64.lib
ezcad/dialogs/__init__.cp37-win_amd64.pyd
ezcad/dialogs/app_config.cp37-win_amd64.exp
ezcad/dialogs/app_config.cp37-win_amd64.lib
ezcad/dialogs/app_config.cp37-win_amd64.pyd
ezcad/dialogs/camera_operator.cp37-win_amd64.exp
ezcad/dialogs/camera_operator.cp37-win_amd64.lib
ezcad/dialogs/camera_operator.cp37-win_amd64.pyd
ezcad/dialogs/colorbar_editor.cp37-win_amd64.exp
ezcad/dialogs/colorbar_editor.cp37-win_amd64.lib
ezcad-0.2.6.dist-info/LICENSE.txt
ezcad-0.2.6.dist-info/METADATA
ezcad-0.2.6.dist-info/WHEEL
ezcad-0.2.6.dist-info/top_level.txt
ezcad-0.2.6.dist-info/RECORD
