Metadata-Version: 2.1
Name: ezcad
Version: 0.2.6
Summary: Easy computer-aided design
Home-page: http://ezcad.org
Author: ezcad team
Author-email: ezcad.dev@gmail.com
License: UNKNOWN
Platform: UNKNOWN
Requires-Dist: chardet
Requires-Dist: cycler
Requires-Dist: freetype-py
Requires-Dist: joblib
Requires-Dist: kiwisolver
Requires-Dist: lxml
Requires-Dist: matplotlib
Requires-Dist: numpy
Requires-Dist: pandas
Requires-Dist: PyOpenGL
Requires-Dist: pyparsing
Requires-Dist: PyQt5
Requires-Dist: pyqtgraph (>=0.11.0rc0)
Requires-Dist: python-dateutil
Requires-Dist: python-dotenv
Requires-Dist: pytz
Requires-Dist: QtAwesome
Requires-Dist: QtPy
Requires-Dist: scipy
Requires-Dist: six
Requires-Dist: vispy
Requires-Dist: Yapsy
